README
kry.py
pyproject.toml
kry_test_2025.egg-info/PKG-INFO
kry_test_2025.egg-info/SOURCES.txt
kry_test_2025.egg-info/dependency_links.txt
kry_test_2025.egg-info/top_level.txt