Metadata-Version: 2.4
Name: kry-test-2025
Version: 2025.5.22
Summary: kry.py - Simple cryptography library
License-Expression: 0BSD
Project-URL: homepage, https://github.com/krylib/kry
Classifier: Topic :: Security :: Cryptography
